family_resources_survey/__init__.py
family_resources_survey/load.py
family_resources_survey/main.py
family_resources_survey/save.py
family_resources_survey-1.0.0.dist-info/METADATA
family_resources_survey-1.0.0.dist-info/WHEEL
family_resources_survey-1.0.0.dist-info/entry_points.txt
family_resources_survey-1.0.0.dist-info/top_level.txt
family_resources_survey-1.0.0.dist-info/RECORD
