Metadata-Version: 2.1
Name: family-resources-survey
Version: 1.0.0
Summary: A Python package to manage Family Resources Survey microdata.
Home-page: http://github.com/nikhilwoodruff/family_resources_survey
Author: Nikhil Woodruff
Author-email: nikhil.woodruff@outlook.com
License: UNKNOWN
Platform: UNKNOWN
Requires-Dist: pandas
Requires-Dist: openpyxl
Requires-Dist: xlrd
